tokenization_scorer/__init__.py
tokenization_scorer/metrics.py
tokenization_scorer/test.py
tokenization_scorer-1.1.8.dist-info/LICENSE
tokenization_scorer-1.1.8.dist-info/METADATA
tokenization_scorer-1.1.8.dist-info/WHEEL
tokenization_scorer-1.1.8.dist-info/entry_points.txt
tokenization_scorer-1.1.8.dist-info/top_level.txt
tokenization_scorer-1.1.8.dist-info/RECORD
