Metadata-Version: 2.2
Name: tokenization-scorer
Version: 1.1.8
Summary: Package for evaluating text tokenizations.
Author-email: Vilém Zouhar <vilem.zouhar@gmail.com>
License: MIT License
Project-URL: Repository, https://github.com/zouharvi/tokenization-scorer
Project-URL: Issues, https://github.com/zouharvi/tokenization-scorer/issues
Keywords: tokenization,evaluation,natural language processing
Requires-Python: >=3.11
License-File: LICENSE
Requires-Dist: tqdm>=4.0
Requires-Dist: numpy>=2.0
